cellface/__init__.py
cellface-0.0.1.dist-info/METADATA
cellface-0.0.1.dist-info/WHEEL
cellface-0.0.1.dist-info/top_level.txt
cellface-0.0.1.dist-info/RECORD
