Metadata-Version: 2.1
Name: cellface
Version: 0.0.1
Summary: Tools for working with digital holographic microscopy images
Home-page: UNKNOWN
Author: Stefan Röhrl
Author-email: r.strice@gmail.com
License: MIT
Platform: UNKNOWN
